memnoch/core/_global_/__init__.py
memnoch/core/_global_/skeleton.py
core_global-1.0.0.dist-info/LICENSE.txt
core_global-1.0.0.dist-info/METADATA
core_global-1.0.0.dist-info/WHEEL
core_global-1.0.0.dist-info/top_level.txt
core_global-1.0.0.dist-info/RECORD
