Metadata-Version: 2.1
Name: core_global
Version: 1.0.0
Summary: Add a short description here!
Home-page: https://github.com/pyscaffold/pyscaffold/
Author: memnoch7891
Author-email: guillaume@ldmail.fr
License: MIT
Project-URL: Documentation, https://pyscaffold.org/
Platform: any
Classifier: Development Status :: 4 - Beta
Classifier: Programming Language :: Python
License-File: LICENSE.txt
Requires-Dist: importlib-metadata; python_version < "3.8"
Provides-Extra: testing
Requires-Dist: setuptools; extra == "testing"
Requires-Dist: pytest; extra == "testing"
Requires-Dist: pytest-cov; extra == "testing"
